euros/__init__.py
euros/en.py
euros/fr.py
euros/it.py
euros/test_en.py
euros/test_fr.py
euros/test_it.py
euros-2.0.1.dist-info/LICENSE
euros-2.0.1.dist-info/METADATA
euros-2.0.1.dist-info/WHEEL
euros-2.0.1.dist-info/top_level.txt
euros-2.0.1.dist-info/RECORD
