Metadata-Version: 2.1
Name: euros
Version: 2.0.1
Summary: Converts euros number to text
Author-email: Thibaut_S <py@spriet.online>
License: MIT-License
Project-URL: Homepage, https://gitlab.com/outils-jcp/euros
Project-URL: Bug Tracker, https://gitlab.com/outils-jcp/euros/-/issues
Keywords: conversion,euros,french,italian,english
Classifier: Programming Language :: Python :: 3
Requires-Python: >=3.8
License-File: LICENSE
Provides-Extra: dev
Requires-Dist: pytest ; extra == 'dev'
Requires-Dist: ruff ; extra == 'dev'
Requires-Dist: black ; extra == 'dev'
Requires-Dist: pip-tools ; extra == 'dev'
Requires-Dist: twine ; extra == 'dev'
